download_tool_pkg/__init__.py
download_tool_pkg/dt.py
springbuk_de_bucket_download-0.0.1.dist-info/LICENSE
springbuk_de_bucket_download-0.0.1.dist-info/METADATA
springbuk_de_bucket_download-0.0.1.dist-info/WHEEL
springbuk_de_bucket_download-0.0.1.dist-info/top_level.txt
springbuk_de_bucket_download-0.0.1.dist-info/RECORD
